time_yang_mcp/__init__.py
time_yang_mcp/__main__.py
time_yang_mcp/server.py
time_yang_mcp-0.1.3.dist-info/LICENSE
time_yang_mcp-0.1.3.dist-info/METADATA
time_yang_mcp-0.1.3.dist-info/WHEEL
time_yang_mcp-0.1.3.dist-info/entry_points.txt
time_yang_mcp-0.1.3.dist-info/top_level.txt
time_yang_mcp-0.1.3.dist-info/RECORD
